README.md
setup.py
Memrise_Scraper.egg-info/PKG-INFO
Memrise_Scraper.egg-info/SOURCES.txt
Memrise_Scraper.egg-info/dependency_links.txt
Memrise_Scraper.egg-info/entry_points.txt
Memrise_Scraper.egg-info/requires.txt
Memrise_Scraper.egg-info/top_level.txt
memrise_scraper/__init__.py
memrise_scraper/memrise.py
memrise_scraper/memrise2tts.py