Metadata-Version: 1.1
Name: Memrise-Scraper
Version: 0.1.0
Summary: UNKNOWN
Home-page: https://github.com/nad2000/memrise-scraper
Author: Radomirs Cirskis
Author-email: nad2000@gmail.com
License: MIT
Keywords: memrise,scraping,scraper,tts,audio
Platform: UNKNOWN
Classifier: Development Status :: 3 - Alpha
Classifier: Intended Audience :: Developers
Classifier: Intended Audience :: Science/Research
Classifier: Natural Language :: English
Classifier: License :: OSI Approved :: MIT License
Classifier: Operating System :: OS Independent
Classifier: Programming Language :: Python
Classifier: Programming Language :: Python :: 3.4
Classifier: Programming Language :: Python :: 3.5
Classifier: Programming Language :: Python :: 3.6
